honeybadger_mcp_server/__init__.py
honeybadger_mcp_server/__main__.py
honeybadger_mcp_server/api.py
honeybadger_mcp_server/server.py
honeybadger_mcp_server-0.2.1.dist-info/METADATA
honeybadger_mcp_server-0.2.1.dist-info/WHEEL
honeybadger_mcp_server-0.2.1.dist-info/entry_points.txt
honeybadger_mcp_server-0.2.1.dist-info/licenses/LICENSE
honeybadger_mcp_server-0.2.1.dist-info/RECORD
