Metadata-Version: 2.4
Name: honeybadger-mcp-server
Version: 0.2.1
Summary: A Model Context Protocol server providing tools to interact with the Honeybadger API via LLMs
Author: Bobby Battista
License: MIT
License-File: LICENSE
Keywords: automation,errors,honeybadger,llm,mcp
Classifier: Development Status :: 4 - Beta
Classifier: Intended Audience :: Developers
Classifier: License :: OSI Approved :: MIT License
Classifier: Programming Language :: Python :: 3
Classifier: Programming Language :: Python :: 3.10
Requires-Python: >=3.10
Requires-Dist: aiohttp==3.11.0
Requires-Dist: click>=8.1.7
Requires-Dist: fastmcp>=2.2.1
Requires-Dist: mcp>=1.6.0
Requires-Dist: pydantic>=2.11.3
Provides-Extra: dev
Requires-Dist: pyright>=1.1.389; extra == 'dev'
Requires-Dist: pytest-asyncio>=0.23.0; extra == 'dev'
Requires-Dist: pytest-mock>=3.12.0; extra == 'dev'
Requires-Dist: pytest>=8.0.0; extra == 'dev'
Requires-Dist: ruff>=0.7.3; extra == 'dev'
